klujax.py
klujax_cpp.cp314-win_amd64.pyd
klujax-0.4.5.dist-info/licenses/LICENSE
klujax-0.4.5.dist-info/METADATA
klujax-0.4.5.dist-info/WHEEL
klujax-0.4.5.dist-info/top_level.txt
klujax-0.4.5.dist-info/RECORD
