Metadata-Version: 2.4
Name: klujax
Version: 0.4.5
Summary: a KLU solver for JAX
Author-email: Floris Laporte <floris.laporte@gmail.com>
License:                   GNU LESSER GENERAL PUBLIC LICENSE
Classifier: Development Status :: 3 - Alpha
Classifier: Programming Language :: Python :: 3
Classifier: Programming Language :: Python :: 3.11
Classifier: Programming Language :: Python :: 3.12
Classifier: Programming Language :: Python :: 3.13
Classifier: Programming Language :: Python :: 3.14
Classifier: License :: OSI Approved :: GNU Lesser General Public License v2 (LGPLv2)
Classifier: Operating System :: OS Independent
Classifier: Topic :: Scientific/Engineering :: Mathematics
Requires-Python: >=3.11
License-File: LICENSE
Requires-Dist: jax>=0.5.0
Requires-Dist: jaxlib>=0.5.0
Requires-Dist: jaxtyping>=0.2.38
Requires-Dist: numpy>=2
Provides-Extra: dev
Requires-Dist: build>=1.2.2; extra == "dev"
Requires-Dist: ipykernel>=6.29.5; extra == "dev"
Requires-Dist: pre-commit>=4.1.0; extra == "dev"
Requires-Dist: pytest>=8.3.4; extra == "dev"
Requires-Dist: ruff>=0.9.7; extra == "dev"
Requires-Dist: setuptools>=75.8.0; extra == "dev"
Requires-Dist: tbump>=6.11.0; extra == "dev"
Dynamic: license-file
